calculatorpkg/__init__.py
calculatorpkg/main.py
calculatorpkg-1.0.0.dist-info/LICENSE
calculatorpkg-1.0.0.dist-info/WHEEL
calculatorpkg-1.0.0.dist-info/METADATA
calculatorpkg-1.0.0.dist-info/RECORD
