Metadata-Version: 2.1
Name: calculatorpkg
Version: 1.0.0
Summary: Initiating package
Author-email: Julian Engels <j-e@mail.de>
Classifier: License :: OSI Approved :: MIT License
Project-URL: Home, https://github.com/TuringCollegeSubmissions/jengel-DWWP.1.5
